Metadata-Version: 2.1
Name: wormholepy
Version: 0.2.0
Summary: A package to check Wormhole airdrop
Home-page: https://github.com/bomsauro/wormholepy
Author: Bomsauro
Author-email: bomsauro@gmail.com
License: BSD 2-clause
Platform: UNKNOWN
